{
  "author": "",
  "content": "",
  "description": "एजेन्सी - भारतले एसीसी टी ट्वान्टी एसिया कपमा पाकिस्तानविरुद्ध टस जितेर पहिला फिल्डिङ गर्ने निर्णय लिएकोछ । दुबई क्रिकेट रंगशालामा भारतका कप्तान सूर्यकुमार यादवले टस जितेर पहिला फिल्डिङ गर्ने निर्णय लिएका छन् । भारत र पाकिस्तान दुबैले टोलीमा दुई परिवर्तन गरेका छन् । भारतले पछिल्लो खेलमा ओमानविरुद्ध खेलेका हर्षित राना र अर्शदीप सिंहलाई बेन्चमा राख्दै",
  "domain": "hamrokhelkud.com",
  "enhanced": true,
  "fetched_at": "2025-09-23T14:58:19.237541Z",
  "id": "a344e183c1cc60c01f61289a127e070bb30eaaaf205f318445c72cd2a4a7317c",
  "images": [],
  "language": "en",
  "metadata": {
    "json_ld": [
      {
        "@context": "https://schema.org",
        "@graph": [
          {
            "@id": "https://www.hamrokhelkud.com/cricket/165877.html#blogposting",
            "@type": "BlogPosting",
            "articleSection": "Featured, क्रिकेट",
            "author": {
              "@id": "https://www.hamrokhelkud.com/author/bhupendra#author"
            },
            "dateModified": "2025-09-21T20:03:21+05:45",
            "datePublished": "2025-09-21T19:54:42+05:45",
            "headline": "भारतले टस जित्यो, सूर्य हात नमिलाई फर्किए",
            "image": {
              "@type": "ImageObject",
              "caption": "Surya Kumar Yadav captain of India and Salman Agha captain of Pakistan during the toss of the Match 6 of the DP World Asia Cup 2025 between India and Pakistan at Dubai International Stadium, Dubai, United Arab Emirates, on 14th September 2025.\n\nPhoto by Vipin Pawar / Creimas for Asian Cricket Council",
              "height": 800,
              "url": "https://www.hamrokhelkud.com/wp-content/uploads/2025/09/india-vs-pakistan.jpg",
              "width": 1200
            },
            "inLanguage": "en-US",
            "isPartOf": {
              "@id": "https://www.hamrokhelkud.com/cricket/165877.html#webpage"
            },
            "mainEntityOfPage": {
              "@id": "https://www.hamrokhelkud.com/cricket/165877.html#webpage"
            },
            "name": "भारतले टस जित्यो, सूर्य हात नमिलाई फर्किए - हाम्रो खेलकुद",
            "publisher": {
              "@id": "https://www.hamrokhelkud.com/#organization"
            }
          },
          {
            "@id": "https://www.hamrokhelkud.com/cricket/165877.html#breadcrumblist",
            "@type": "BreadcrumbList",
            "itemListElement": [
              {
                "@id": "https://www.hamrokhelkud.com/#listItem",
                "@type": "ListItem",
                "item": "https://www.hamrokhelkud.com/",
                "name": "Home",
                "nextItem": "https://www.hamrokhelkud.com/category/cricket#listItem",
                "position": 1
              },
              {
                "@id": "https://www.hamrokhelkud.com/category/cricket#listItem",
                "@type": "ListItem",
                "name": "क्रिकेट",
                "position": 2,
                "previousItem": "https://www.hamrokhelkud.com/#listItem"
              }
            ]
          },
          {
            "@id": "https://www.hamrokhelkud.com/#organization",
            "@type": "Organization",
            "image": {
              "@id": "https://www.hamrokhelkud.com/#organizationLogo"
            },
            "logo": {
              "@id": "https://www.hamrokhelkud.com/cricket/165877.html/#organizationLogo",
              "@type": "ImageObject",
              "height": 644,
              "url": "https://www.hamrokhelkud.com/wp-content/uploads/2023/08/Branding-1-1-1-3.png",
              "width": 1473
            },
            "name": "Hamro Khelkud",
            "url": "https://www.hamrokhelkud.com/"
          },
          {
            "@id": "https://www.hamrokhelkud.com/author/bhupendra#author",
            "@type": "Person",
            "image": {
              "@id": "https://www.hamrokhelkud.com/cricket/165877.html#authorImage",
              "@type": "ImageObject",
              "caption": "Bhupendra GC",
              "height": 96,
              "url": "https://secure.gravatar.com/avatar/7bdec1a4daf362fbb3c4176e7f0b35b2?s=96&d=mm&r=g",
              "width": 96
            },
            "name": "Bhupendra GC",
            "url": "https://www.hamrokhelkud.com/author/bhupendra"
          },
          {
            "@id": "https://www.hamrokhelkud.com/cricket/165877.html#webpage",
            "@type": "WebPage",
            "author": {
              "@id": "https://www.hamrokhelkud.com/author/bhupendra#author"
            },
            "breadcrumb": {
              "@id": "https://www.hamrokhelkud.com/cricket/165877.html#breadcrumblist"
            },
            "creator": {
              "@id": "https://www.hamrokhelkud.com/author/bhupendra#author"
            },
            "dateModified": "2025-09-21T20:03:21+05:45",
            "datePublished": "2025-09-21T19:54:42+05:45",
            "description": "एजेन्सी - भारतले एसीसी टी ट्वान्टी एसिया कपमा पाकिस्तानविरुद्ध टस जितेर पहिला फिल्डिङ गर्ने निर्णय लिएकोछ । दुबई क्रिकेट रंगशालामा भारतका कप्तान सूर्यकुमार यादवले टस जितेर पहिला फिल्डिङ गर्ने निर्णय लिएका छन् । भारत र पाकिस्तान दुबैले टोलीमा दुई परिवर्तन गरेका छन् । भारतले पछिल्लो खेलमा ओमानविरुद्ध खेलेका हर्षित राना र अर्शदीप सिंहलाई बेन्चमा राख्दै",
            "image": {
              "@id": "https://www.hamrokhelkud.com/cricket/165877.html/#mainImage",
              "@type": "ImageObject",
              "caption": "Surya Kumar Yadav captain of India and Salman Agha captain of Pakistan during the toss of the Match 6 of the DP World Asia Cup 2025 between India and Pakistan at Dubai International Stadium, Dubai, United Arab Emirates, on 14th September 2025.\n\nPhoto by Vipin Pawar / Creimas for Asian Cricket Council",
              "height": 800,
              "url": "https://www.hamrokhelkud.com/wp-content/uploads/2025/09/india-vs-pakistan.jpg",
              "width": 1200
            },
            "inLanguage": "en-US",
            "isPartOf": {
              "@id": "https://www.hamrokhelkud.com/#website"
            },
            "name": "भारतले टस जित्यो, सूर्य हात नमिलाई फर्किए - हाम्रो खेलकुद",
            "primaryImageOfPage": {
              "@id": "https://www.hamrokhelkud.com/cricket/165877.html#mainImage"
            },
            "url": "https://www.hamrokhelkud.com/cricket/165877.html"
          },
          {
            "@id": "https://www.hamrokhelkud.com/#website",
            "@type": "WebSite",
            "description": "HamroKhelkud.com - Complete website for Nepali Sports News | Nepali Cricket, Football and More",
            "inLanguage": "en-US",
            "name": "Hamro Khelkud",
            "publisher": {
              "@id": "https://www.hamrokhelkud.com/#organization"
            },
            "url": "https://www.hamrokhelkud.com/"
          }
        ]
      }
    ],
    "microdata": [
      {
        "type": "http://schema.org/WebPage",
        "value": "23-09-2025 20:21:17pm\n\nविज्ञापन एप डाउनलोड\n\nफुटबल\nक्रिकेट\nभलिबल\nअन्तर्राष्ट्रिय\nअन्य\n\nमार्सल आर्टस्\n\nतेक्वान्दो\nकराते\nबक्सिङ\nजुडो\nउसु\nमुवाँथाई\n\nर्याकेट खेल\n\nटेनिस\nटेबल टेनिस\nब्याडमिन्टन\n\nई-स्पोर्ट्स\nगल्फ\nबास्केटबल\nएथलेटिक्स\nआउटडोर\n\nरग्बी\nहक्की\nस्की\nआर्चरी\n\nइनडोर\n\nपौडी\nस्क्वास\nबुद्धिचाल\nकुस्ती\nह्यान्डबल\nभारोत्तोलन\nस्नुकर\nसुटिङ\nफेन्सिङ\nरेस्लिङ\nकबड्डी\n\nफोटो ग्यालरी\nप्रतियोगिता\n\nफुटबल\n\nआहा! रारा गोल्ड कप\nएन्फा महिला लिग\n\n२०२५\n\nछनोट\n\n२०२४\n\n२०२६ विश्वकप छनोट – दोस्रो चरण\nए डिभिजन लिग\n\n२०७९\n२०७८\n\nबी डिभिजन\n\n२०८१\n२०७८\n\nयू१६ लिग\n\n२०२५\n२०२३\n\nअन्तर्राष्ट्रिय\n\nसाफ पुरुष\n\n२०२३\n\nनेपाल सुपर लिग\n\nएनएसएल ३ – २०२५\nएनएसएल २ – २०२३\nएनएसएल १ – २०२१\n\nसाफ यू-१९ २०२३\n\nभलिबल\n\n३४ औं राष्ट्रिय पुरुष भलिबल\nमहिला\n\nएनभिए लिग\n\nसातौं\n\nअन्तर्राष्ट्रिय\n\nकाभा महिला च्यालेन्ज कप\n\nपुरुष\n\nएनभिए लिग\n\nसातौं\n\nअन्तर्राष्ट्रिय\n\nकाभा पुरुष नेसन्स लिग\n\nएनएसएल-३\n\nEnglish\n\nSign In\n\nHome\nक्रिकेट\nभारतले टस जित्यो, सूर्य हात नमिलाई फर्किए\n\n2 days ago\n\nSeptember 21, 2025\n\nभारतले टस जित्यो, सूर्य हात नमिलाई फर्किए\n\n0 Likes\n\n1898 views\n\n0 Bookmark\n\nएजेन्सी – भारतले एसीसी टी ट्वान्टी एसिया कपमा पाकिस्तानविरुद्ध टस जितेर पहिला फिल्डिङ गर्ने निर्णय लिएकोछ । दुबई क्रिकेट रंगशालामा भारतका कप्तान सूर्यकुमार यादवले टस जितेर पहिला फिल्डिङ गर्ने निर्णय लिएका छन् ।\n\nभारत र पाकिस्तान दुबैले टोलीमा दुई परिवर्तन गरेका छन् । भारतले पछिल्लो खेलमा ओमानविरुद्ध खेलेका हर्षित राना र अर्शदीप सिंहलाई बेन्चमा राख्दै जस्प्रित बुमराह र बरुण चक्रवर्तीलाई मैदान उतारेको छ । पाकिस्तानले पछिल्लो खेलमा युएईविरुद्ध खेलबाट हसन नवाज र खुशदील शाहलाई बेन्चमा राख्दा हुसेन तालत र फहिम अशरफलाई आज खेलाएको छ ।\n\nसमूह चरणमा दुबै टोलीले हात मिलाएका थिएनन् । टसमा पनि दुबै कप्तानले हात मिलाएका थिएनन् । ठूलो विवादकाबीच खेलेका यी दुई देशका कप्तानले आजको खेलमा एकले अर्कालाई टसको समयमा हेरेनन् । टस जितेर सूर्य हात नमिलाई फर्किएका छन् ।\n\nपाकिस्तानको प्लेइङ ११\n\nशहिबजादा फरान, सैम अयुब, फखर जमान, सलमान अली अघा, हुसेन तालत, मोहम्मद नवाज, शाहिन शाह अफ्रिदी, हरिस रौफ, मोहम्मद हरिस, अब्रार अहमद र फहिम अशरफ ।\n\nभारतको प्लेइङ ११ :\n\nअभिषेक शर्मा, शुभमन गिल, सन्जु स्यामसन, सूर्यकुमार यादव, तिलक बर्मा, हार्दिक पान्ड्या, अक्षर पटेल, बरुण चक्रवर्ती, कुलदीप यादव, जस्प्रित बुमराह र शिबम दुबे ।\n\nShare this News:\nFacebook 0 Tweet 0 Pin 0\n\nLatest News\n\nझापा महिला गोल्डकपको विजेताले १० लाख पाउने September 23, 2025\nडेम्बेले र बोनमातीलाई ब्यालोन डि’ओर अवार्ड September 23, 2025\nपिएसजी पराजित September 23, 2025\n\nAll Latest News\n\nPopular News\n\nझापा महिला गोल्डकपको विजेताले १० लाख पाउने September 23, 2025\nडेम्बेले र बोनमातीलाई ब्यालोन डि’ओर अवार्ड September 23, 2025\nपिएसजी पराजित September 23, 2025\n\nक्रिकेट\n\nसबै क्रिकेट समाचार\n\nSeptember 22, 2025\n\nपाकिस्तानमाथि भारतको सानदार जित\n\nएजेन्सी – ओपनर अभिषेक शर्माको अर्धशतकको सहयोगमा भारतले एसीसी टीट्वान्टी एसिया कपको सुपर फोरमा पाकिस्तानलाई ६ विकेटले पराजित गरेको छ । जित्नलाई १ सय ७२ रनको लक्ष्य पछ्याएको भारतले १८.४ ओेभरमा ४ विकेट गुमाउँदै पूरा गर्यो । भारतका अभिषेक शर्माले ३९ बलमा ६ चौका र ५ छक्कासहित सर्वाधिक ७४ रन बनाए । शुभमन गिलले २८ […]\n\nSeptember 21, 2025\n\nभारतलाई पाकिस्तानको प्रतिस्पर्धात्मक लक्ष्य\n\nएजेन्सी – ओपनर शहिबजादा फरानको अर्धशतकको सहयोगमा पाकिस्तानले एसीसी टी ट्वान्टी एसिया कपमा भारतलाई १ सय ७२ रनको प्रतिस्पर्धात्मक लक्ष्य दिएको छ । दुबई अन्तर्राष्ट्रिय क्रिकेट रंगशालामा टस हारेर पहिला ब्याटिङको निम्तो पाएको पाकिस्तानले २० ओभरमा ५ विकेट गुमाउँदै १ सय ७१ रन बनायो । पाकिस्तानका ओपनर शहिबजादा फरानले ४५ बलमा ५ चौका र ३ […]\n\nSeptember 21, 2025\n\nक्रिकेट टोली भोलि युएई जाने\n\nकाठमाडौं (हाम्रो खेलकुद)- नेपाली राष्ट्रिय क्रिकेट टोलीको युएईको भिसा आएको छ। विश्व विजेता समेत रहिसकेको वेस्ट इन्डिज विरुद्ध ३ खेलको टि ट्वान्टी ऐतिहासिक सिरिज खेल्न नेपाली टोली शुक्रवार युएई जाने तयारी भएपनि भिसा नआएका कारण यात्रा रोकिएको थियो। नेपाल क्रिकेट संघ (क्यान) का अनुसार टोली‌ सोमवार त्यसतर्फ प्रस्थान गर्नेछ। नेपालमा भएको पछिल्लो राजनैतिक घटनापछि युएईले नेपालीलाई […]\n\nहाम्रो मोबाइल एप डाउनलोड गर्नुहोस\n\nहाम्रो खेलकुदको मोबाइल एप डाउनलोड गरेर राष्ट्रिय तथा अन्तर्राष्ट्रिय खेलकुदको समाचार सहज रुपमा पाउनुहोस्\n\nचर्चित खेलहरु:\n\nफुटबल\nअन्तर्राष्ट्रिय\nक्रिकेट\nअन्य\nभलिबल\n\nउपयोगी लिङ्कहरू\n\nहाम्रो बारे\n\nसम्पर्क\n\nसम्पर्क\n\nसामाजिक संजाल\n\nFacebook\nTwitter\nYoutube\nInstagram\n\nप्रेस काउन्सिल प्रमाणपत्र नं : ५२५\nसूचना विभाग दर्ता प्रमाणपत्र नं : १४८३/०७६-०७७\nCopyright © HamroKhelkud, 2023. All rights reserved.\n\nDeveloped by: Makura Creations Pvt. Ltd\n\nJoin our platform for a personalized experience with exclusive content, engaging discussions, and a vibrant community.\n\nSign In\n\nEmail\nPassword\nForget Password ?\nSign In\n\nDon’t have an account? Create account\n\nJoin our platform for a personalized experience with exclusive content, engaging discussions, and a vibrant community.\n\nSign Up\n\nFirst Name\nLast Name\nEmail\nPassword\nConfirm Password\nSign Up\n\nAlready have an account? Sign In\n\nJoin our platform for a personalized experience with exclusive content, engaging discussions, and a vibrant community.\n\nForgot Password\n\nEmail\nCreate\n\nAlready have an account? Sign In\n\nDon’t have an account? Create account\n\nSuccess\n\nThank you for your time.\n\nClose this module\n\nRegister Now"
      }
    ],
    "opengraph": [
      {
        "namespace": {
          "article": "http://ogp.me/ns/article#",
          "og": "http://ogp.me/ns#"
        },
        "properties": [
          [
            "og:locale",
            "en_US"
          ],
          [
            "og:site_name",
            "हाम्रो खेलकुद"
          ],
          [
            "og:type",
            "article"
          ],
          [
            "og:title",
            "भारतले टस जित्यो, सूर्य हात नमिलाई फर्किए - हाम्रो खेलकुद"
          ],
          [
            "og:description",
            "एजेन्सी - भारतले एसीसी टी ट्वान्टी एसिया कपमा पाकिस्तानविरुद्ध टस जितेर पहिला फिल्डिङ गर्ने निर्णय लिएकोछ । दुबई क्रिकेट रंगशालामा भारतका कप्तान सूर्यकुमार यादवले टस जितेर पहिला फिल्डिङ गर्ने निर्णय लिएका छन् । भारत र पाकिस्तान दुबैले टोलीमा दुई परिवर्तन गरेका छन् । भारतले पछिल्लो खेलमा ओमानविरुद्ध खेलेका हर्षित राना र अर्शदीप सिंहलाई बेन्चमा राख्दै"
          ],
          [
            "og:url",
            "https://www.hamrokhelkud.com/cricket/165877.html"
          ],
          [
            "og:image",
            "https://www.hamrokhelkud.com/wp-content/uploads/2025/09/india-vs-pakistan.jpg"
          ],
          [
            "og:image:secure_url",
            "https://www.hamrokhelkud.com/wp-content/uploads/2025/09/india-vs-pakistan.jpg"
          ],
          [
            "og:image:width",
            "1200"
          ],
          [
            "og:image:height",
            "800"
          ],
          [
            "article:published_time",
            "2025-09-21T08:24:42+00:00"
          ],
          [
            "article:modified_time",
            "2025-09-21T08:33:21+00:00"
          ]
        ]
      }
    ],
    "raw": {
      "json-ld": [
        {
          "@context": "https://schema.org",
          "@graph": [
            {
              "@id": "https://www.hamrokhelkud.com/cricket/165877.html#blogposting",
              "@type": "BlogPosting",
              "articleSection": "Featured, क्रिकेट",
              "author": {
                "@id": "https://www.hamrokhelkud.com/author/bhupendra#author"
              },
              "dateModified": "2025-09-21T20:03:21+05:45",
              "datePublished": "2025-09-21T19:54:42+05:45",
              "headline": "भारतले टस जित्यो, सूर्य हात नमिलाई फर्किए",
              "image": {
                "@type": "ImageObject",
                "caption": "Surya Kumar Yadav captain of India and Salman Agha captain of Pakistan during the toss of the Match 6 of the DP World Asia Cup 2025 between India and Pakistan at Dubai International Stadium, Dubai, United Arab Emirates, on 14th September 2025.\n\nPhoto by Vipin Pawar / Creimas for Asian Cricket Council",
                "height": 800,
                "url": "https://www.hamrokhelkud.com/wp-content/uploads/2025/09/india-vs-pakistan.jpg",
                "width": 1200
              },
              "inLanguage": "en-US",
              "isPartOf": {
                "@id": "https://www.hamrokhelkud.com/cricket/165877.html#webpage"
              },
              "mainEntityOfPage": {
                "@id": "https://www.hamrokhelkud.com/cricket/165877.html#webpage"
              },
              "name": "भारतले टस जित्यो, सूर्य हात नमिलाई फर्किए - हाम्रो खेलकुद",
              "publisher": {
                "@id": "https://www.hamrokhelkud.com/#organization"
              }
            },
            {
              "@id": "https://www.hamrokhelkud.com/cricket/165877.html#breadcrumblist",
              "@type": "BreadcrumbList",
              "itemListElement": [
                {
                  "@id": "https://www.hamrokhelkud.com/#listItem",
                  "@type": "ListItem",
                  "item": "https://www.hamrokhelkud.com/",
                  "name": "Home",
                  "nextItem": "https://www.hamrokhelkud.com/category/cricket#listItem",
                  "position": 1
                },
                {
                  "@id": "https://www.hamrokhelkud.com/category/cricket#listItem",
                  "@type": "ListItem",
                  "name": "क्रिकेट",
                  "position": 2,
                  "previousItem": "https://www.hamrokhelkud.com/#listItem"
                }
              ]
            },
            {
              "@id": "https://www.hamrokhelkud.com/#organization",
              "@type": "Organization",
              "image": {
                "@id": "https://www.hamrokhelkud.com/#organizationLogo"
              },
              "logo": {
                "@id": "https://www.hamrokhelkud.com/cricket/165877.html/#organizationLogo",
                "@type": "ImageObject",
                "height": 644,
                "url": "https://www.hamrokhelkud.com/wp-content/uploads/2023/08/Branding-1-1-1-3.png",
                "width": 1473
              },
              "name": "Hamro Khelkud",
              "url": "https://www.hamrokhelkud.com/"
            },
            {
              "@id": "https://www.hamrokhelkud.com/author/bhupendra#author",
              "@type": "Person",
              "image": {
                "@id": "https://www.hamrokhelkud.com/cricket/165877.html#authorImage",
                "@type": "ImageObject",
                "caption": "Bhupendra GC",
                "height": 96,
                "url": "https://secure.gravatar.com/avatar/7bdec1a4daf362fbb3c4176e7f0b35b2?s=96&d=mm&r=g",
                "width": 96
              },
              "name": "Bhupendra GC",
              "url": "https://www.hamrokhelkud.com/author/bhupendra"
            },
            {
              "@id": "https://www.hamrokhelkud.com/cricket/165877.html#webpage",
              "@type": "WebPage",
              "author": {
                "@id": "https://www.hamrokhelkud.com/author/bhupendra#author"
              },
              "breadcrumb": {
                "@id": "https://www.hamrokhelkud.com/cricket/165877.html#breadcrumblist"
              },
              "creator": {
                "@id": "https://www.hamrokhelkud.com/author/bhupendra#author"
              },
              "dateModified": "2025-09-21T20:03:21+05:45",
              "datePublished": "2025-09-21T19:54:42+05:45",
              "description": "एजेन्सी - भारतले एसीसी टी ट्वान्टी एसिया कपमा पाकिस्तानविरुद्ध टस जितेर पहिला फिल्डिङ गर्ने निर्णय लिएकोछ । दुबई क्रिकेट रंगशालामा भारतका कप्तान सूर्यकुमार यादवले टस जितेर पहिला फिल्डिङ गर्ने निर्णय लिएका छन् । भारत र पाकिस्तान दुबैले टोलीमा दुई परिवर्तन गरेका छन् । भारतले पछिल्लो खेलमा ओमानविरुद्ध खेलेका हर्षित राना र अर्शदीप सिंहलाई बेन्चमा राख्दै",
              "image": {
                "@id": "https://www.hamrokhelkud.com/cricket/165877.html/#mainImage",
                "@type": "ImageObject",
                "caption": "Surya Kumar Yadav captain of India and Salman Agha captain of Pakistan during the toss of the Match 6 of the DP World Asia Cup 2025 between India and Pakistan at Dubai International Stadium, Dubai, United Arab Emirates, on 14th September 2025.\n\nPhoto by Vipin Pawar / Creimas for Asian Cricket Council",
                "height": 800,
                "url": "https://www.hamrokhelkud.com/wp-content/uploads/2025/09/india-vs-pakistan.jpg",
                "width": 1200
              },
              "inLanguage": "en-US",
              "isPartOf": {
                "@id": "https://www.hamrokhelkud.com/#website"
              },
              "name": "भारतले टस जित्यो, सूर्य हात नमिलाई फर्किए - हाम्रो खेलकुद",
              "primaryImageOfPage": {
                "@id": "https://www.hamrokhelkud.com/cricket/165877.html#mainImage"
              },
              "url": "https://www.hamrokhelkud.com/cricket/165877.html"
            },
            {
              "@id": "https://www.hamrokhelkud.com/#website",
              "@type": "WebSite",
              "description": "HamroKhelkud.com - Complete website for Nepali Sports News | Nepali Cricket, Football and More",
              "inLanguage": "en-US",
              "name": "Hamro Khelkud",
              "publisher": {
                "@id": "https://www.hamrokhelkud.com/#organization"
              },
              "url": "https://www.hamrokhelkud.com/"
            }
          ]
        }
      ],
      "microdata": [
        {
          "type": "http://schema.org/WebPage",
          "value": "23-09-2025 20:21:17pm\n\nविज्ञापन एप डाउनलोड\n\nफुटबल\nक्रिकेट\nभलिबल\nअन्तर्राष्ट्रिय\nअन्य\n\nमार्सल आर्टस्\n\nतेक्वान्दो\nकराते\nबक्सिङ\nजुडो\nउसु\nमुवाँथाई\n\nर्याकेट खेल\n\nटेनिस\nटेबल टेनिस\nब्याडमिन्टन\n\nई-स्पोर्ट्स\nगल्फ\nबास्केटबल\nएथलेटिक्स\nआउटडोर\n\nरग्बी\nहक्की\nस्की\nआर्चरी\n\nइनडोर\n\nपौडी\nस्क्वास\nबुद्धिचाल\nकुस्ती\nह्यान्डबल\nभारोत्तोलन\nस्नुकर\nसुटिङ\nफेन्सिङ\nरेस्लिङ\nकबड्डी\n\nफोटो ग्यालरी\nप्रतियोगिता\n\nफुटबल\n\nआहा! रारा गोल्ड कप\nएन्फा महिला लिग\n\n२०२५\n\nछनोट\n\n२०२४\n\n२०२६ विश्वकप छनोट – दोस्रो चरण\nए डिभिजन लिग\n\n२०७९\n२०७८\n\nबी डिभिजन\n\n२०८१\n२०७८\n\nयू१६ लिग\n\n२०२५\n२०२३\n\nअन्तर्राष्ट्रिय\n\nसाफ पुरुष\n\n२०२३\n\nनेपाल सुपर लिग\n\nएनएसएल ३ – २०२५\nएनएसएल २ – २०२३\nएनएसएल १ – २०२१\n\nसाफ यू-१९ २०२३\n\nभलिबल\n\n३४ औं राष्ट्रिय पुरुष भलिबल\nमहिला\n\nएनभिए लिग\n\nसातौं\n\nअन्तर्राष्ट्रिय\n\nकाभा महिला च्यालेन्ज कप\n\nपुरुष\n\nएनभिए लिग\n\nसातौं\n\nअन्तर्राष्ट्रिय\n\nकाभा पुरुष नेसन्स लिग\n\nएनएसएल-३\n\nEnglish\n\nSign In\n\nHome\nक्रिकेट\nभारतले टस जित्यो, सूर्य हात नमिलाई फर्किए\n\n2 days ago\n\nSeptember 21, 2025\n\nभारतले टस जित्यो, सूर्य हात नमिलाई फर्किए\n\n0 Likes\n\n1898 views\n\n0 Bookmark\n\nएजेन्सी – भारतले एसीसी टी ट्वान्टी एसिया कपमा पाकिस्तानविरुद्ध टस जितेर पहिला फिल्डिङ गर्ने निर्णय लिएकोछ । दुबई क्रिकेट रंगशालामा भारतका कप्तान सूर्यकुमार यादवले टस जितेर पहिला फिल्डिङ गर्ने निर्णय लिएका छन् ।\n\nभारत र पाकिस्तान दुबैले टोलीमा दुई परिवर्तन गरेका छन् । भारतले पछिल्लो खेलमा ओमानविरुद्ध खेलेका हर्षित राना र अर्शदीप सिंहलाई बेन्चमा राख्दै जस्प्रित बुमराह र बरुण चक्रवर्तीलाई मैदान उतारेको छ । पाकिस्तानले पछिल्लो खेलमा युएईविरुद्ध खेलबाट हसन नवाज र खुशदील शाहलाई बेन्चमा राख्दा हुसेन तालत र फहिम अशरफलाई आज खेलाएको छ ।\n\nसमूह चरणमा दुबै टोलीले हात मिलाएका थिएनन् । टसमा पनि दुबै कप्तानले हात मिलाएका थिएनन् । ठूलो विवादकाबीच खेलेका यी दुई देशका कप्तानले आजको खेलमा एकले अर्कालाई टसको समयमा हेरेनन् । टस जितेर सूर्य हात नमिलाई फर्किएका छन् ।\n\nपाकिस्तानको प्लेइङ ११\n\nशहिबजादा फरान, सैम अयुब, फखर जमान, सलमान अली अघा, हुसेन तालत, मोहम्मद नवाज, शाहिन शाह अफ्रिदी, हरिस रौफ, मोहम्मद हरिस, अब्रार अहमद र फहिम अशरफ ।\n\nभारतको प्लेइङ ११ :\n\nअभिषेक शर्मा, शुभमन गिल, सन्जु स्यामसन, सूर्यकुमार यादव, तिलक बर्मा, हार्दिक पान्ड्या, अक्षर पटेल, बरुण चक्रवर्ती, कुलदीप यादव, जस्प्रित बुमराह र शिबम दुबे ।\n\nShare this News:\nFacebook 0 Tweet 0 Pin 0\n\nLatest News\n\nझापा महिला गोल्डकपको विजेताले १० लाख पाउने September 23, 2025\nडेम्बेले र बोनमातीलाई ब्यालोन डि’ओर अवार्ड September 23, 2025\nपिएसजी पराजित September 23, 2025\n\nAll Latest News\n\nPopular News\n\nझापा महिला गोल्डकपको विजेताले १० लाख पाउने September 23, 2025\nडेम्बेले र बोनमातीलाई ब्यालोन डि’ओर अवार्ड September 23, 2025\nपिएसजी पराजित September 23, 2025\n\nक्रिकेट\n\nसबै क्रिकेट समाचार\n\nSeptember 22, 2025\n\nपाकिस्तानमाथि भारतको सानदार जित\n\nएजेन्सी – ओपनर अभिषेक शर्माको अर्धशतकको सहयोगमा भारतले एसीसी टीट्वान्टी एसिया कपको सुपर फोरमा पाकिस्तानलाई ६ विकेटले पराजित गरेको छ । जित्नलाई १ सय ७२ रनको लक्ष्य पछ्याएको भारतले १८.४ ओेभरमा ४ विकेट गुमाउँदै पूरा गर्यो । भारतका अभिषेक शर्माले ३९ बलमा ६ चौका र ५ छक्कासहित सर्वाधिक ७४ रन बनाए । शुभमन गिलले २८ […]\n\nSeptember 21, 2025\n\nभारतलाई पाकिस्तानको प्रतिस्पर्धात्मक लक्ष्य\n\nएजेन्सी – ओपनर शहिबजादा फरानको अर्धशतकको सहयोगमा पाकिस्तानले एसीसी टी ट्वान्टी एसिया कपमा भारतलाई १ सय ७२ रनको प्रतिस्पर्धात्मक लक्ष्य दिएको छ । दुबई अन्तर्राष्ट्रिय क्रिकेट रंगशालामा टस हारेर पहिला ब्याटिङको निम्तो पाएको पाकिस्तानले २० ओभरमा ५ विकेट गुमाउँदै १ सय ७१ रन बनायो । पाकिस्तानका ओपनर शहिबजादा फरानले ४५ बलमा ५ चौका र ३ […]\n\nSeptember 21, 2025\n\nक्रिकेट टोली भोलि युएई जाने\n\nकाठमाडौं (हाम्रो खेलकुद)- नेपाली राष्ट्रिय क्रिकेट टोलीको युएईको भिसा आएको छ। विश्व विजेता समेत रहिसकेको वेस्ट इन्डिज विरुद्ध ३ खेलको टि ट्वान्टी ऐतिहासिक सिरिज खेल्न नेपाली टोली शुक्रवार युएई जाने तयारी भएपनि भिसा नआएका कारण यात्रा रोकिएको थियो। नेपाल क्रिकेट संघ (क्यान) का अनुसार टोली‌ सोमवार त्यसतर्फ प्रस्थान गर्नेछ। नेपालमा भएको पछिल्लो राजनैतिक घटनापछि युएईले नेपालीलाई […]\n\nहाम्रो मोबाइल एप डाउनलोड गर्नुहोस\n\nहाम्रो खेलकुदको मोबाइल एप डाउनलोड गरेर राष्ट्रिय तथा अन्तर्राष्ट्रिय खेलकुदको समाचार सहज रुपमा पाउनुहोस्\n\nचर्चित खेलहरु:\n\nफुटबल\nअन्तर्राष्ट्रिय\nक्रिकेट\nअन्य\nभलिबल\n\nउपयोगी लिङ्कहरू\n\nहाम्रो बारे\n\nसम्पर्क\n\nसम्पर्क\n\nसामाजिक संजाल\n\nFacebook\nTwitter\nYoutube\nInstagram\n\nप्रेस काउन्सिल प्रमाणपत्र नं : ५२५\nसूचना विभाग दर्ता प्रमाणपत्र नं : १४८३/०७६-०७७\nCopyright © HamroKhelkud, 2023. All rights reserved.\n\nDeveloped by: Makura Creations Pvt. Ltd\n\nJoin our platform for a personalized experience with exclusive content, engaging discussions, and a vibrant community.\n\nSign In\n\nEmail\nPassword\nForget Password ?\nSign In\n\nDon’t have an account? Create account\n\nJoin our platform for a personalized experience with exclusive content, engaging discussions, and a vibrant community.\n\nSign Up\n\nFirst Name\nLast Name\nEmail\nPassword\nConfirm Password\nSign Up\n\nAlready have an account? Sign In\n\nJoin our platform for a personalized experience with exclusive content, engaging discussions, and a vibrant community.\n\nForgot Password\n\nEmail\nCreate\n\nAlready have an account? Sign In\n\nDon’t have an account? Create account\n\nSuccess\n\nThank you for your time.\n\nClose this module\n\nRegister Now"
        }
      ],
      "opengraph": [
        {
          "namespace": {
            "article": "http://ogp.me/ns/article#",
            "og": "http://ogp.me/ns#"
          },
          "properties": [
            [
              "og:locale",
              "en_US"
            ],
            [
              "og:site_name",
              "हाम्रो खेलकुद"
            ],
            [
              "og:type",
              "article"
            ],
            [
              "og:title",
              "भारतले टस जित्यो, सूर्य हात नमिलाई फर्किए - हाम्रो खेलकुद"
            ],
            [
              "og:description",
              "एजेन्सी - भारतले एसीसी टी ट्वान्टी एसिया कपमा पाकिस्तानविरुद्ध टस जितेर पहिला फिल्डिङ गर्ने निर्णय लिएकोछ । दुबई क्रिकेट रंगशालामा भारतका कप्तान सूर्यकुमार यादवले टस जितेर पहिला फिल्डिङ गर्ने निर्णय लिएका छन् । भारत र पाकिस्तान दुबैले टोलीमा दुई परिवर्तन गरेका छन् । भारतले पछिल्लो खेलमा ओमानविरुद्ध खेलेका हर्षित राना र अर्शदीप सिंहलाई बेन्चमा राख्दै"
            ],
            [
              "og:url",
              "https://www.hamrokhelkud.com/cricket/165877.html"
            ],
            [
              "og:image",
              "https://www.hamrokhelkud.com/wp-content/uploads/2025/09/india-vs-pakistan.jpg"
            ],
            [
              "og:image:secure_url",
              "https://www.hamrokhelkud.com/wp-content/uploads/2025/09/india-vs-pakistan.jpg"
            ],
            [
              "og:image:width",
              "1200"
            ],
            [
              "og:image:height",
              "800"
            ],
            [
              "article:published_time",
              "2025-09-21T08:24:42+00:00"
            ],
            [
              "article:modified_time",
              "2025-09-21T08:33:21+00:00"
            ]
          ]
        }
      ]
    }
  },
  "og_description": "",
  "og_image": "",
  "og_site_name": "",
  "og_title": "",
  "og_type": "",
  "published_at": "2025-09-21T14:09:42Z",
  "source": "Hamro Khelkud",
  "store_path": "_store/a3/a344e183c1cc60c01f61289a127e070bb30eaaaf205f318445c72cd2a4a7317c.json",
  "title": "भारतले टस जित्यो, सूर्य हात नमिलाई फर्किए",
  "url": "https://www.hamrokhelkud.com/cricket/165877.html",
  "version": 1
}