{
  "content": "",
  "description": "काठमाडौँ । सरकारको प्रवक्तामा सञ्चार तथा सूचना मन्त्री जगदीश खरेललाई तोकिएको छ। बिहीबार बसेको मन्त्रिपरिषद्को बैठकले सो निर्णय गरेको हो।",
  "domain": "prasashan.com",
  "fetched_at": "2025-09-25T13:59:17.045492Z",
  "id": "a3813bceaca92195410d7a27d0174f56c8759ce4dc0e5605a6c5fc187c647c98",
  "images": [],
  "published_at": "2025-09-25T13:35:08Z",
  "source": "Prashasan",
  "store_path": "_store/a3/a3813bceaca92195410d7a27d0174f56c8759ce4dc0e5605a6c5fc187c647c98.json",
  "title": "सरकारको प्रवक्तामा सञ्चारमन्त्री खरेललाई तोकियो",
  "url": "https://www.prasashan.com/2025/09/25/704276/",
  "version": 1
}