{
  "canonical_hash": "cf56a33d24d2c09ebe97923c5e1042a5cb0af74f921c707f546d2995cea732ac",
  "fetched_at": "2025-09-18T03:32:06.981848Z",
  "id": "6dc5483bceaccc584707f8e9a56c11653f0a1183b53b66b051943ace6df512b2",
  "images": [
    "https://images.nagariknewscdn.com/third-party/1701478146_ol%20ol%20ol.jpg"
  ],
  "published_at": "2023-12-01T19:09:04Z",
  "source": {
    "domain": "nagariknews.nagariknetwork.com",
    "id": "nagariknews",
    "name": "नागरिक दैनिक"
  },
  "store_path": "domains/_store/6d/6dc5483bceaccc584707f8e9a56c11653f0a1183b53b66b051943ace6df512b2.json",
  "title": "याे पनि",
  "url": "https://nagariknews.nagariknetwork.com/cartoon/1364391-1701478444.html",
  "version": 1
}