{
  "byline": "रिपोर्टर्स नेपाल",
  "canonical_hash": "0aac9a5c2ad1f6072bd12b2e7bca1b22be23498853799819c220261b71a3dd92",
  "content_html": "काठमाडौं, २ असोज । नेपाली कांग्रेसका सहमहामन्त्री जीवन परियारले पार्टीको पुनर्गठनको लागि भन्दै विशेष महाधिवेशनको माग गरेका छन् । अहिलेको कठिन परिस्थितिमा पार्टीको पुनर्गठन, नेतृत्वले त्याग गर्नुपर्ने, नेतृत्वको बहिर्गमनजस्ता विविध मागहरु आइरहेको उल्लेख गर्दै उनले पार्टी विधानको धारा १७ अनुसार विशेष महाधिवेशनको माग गरेका हुन् । ‘पार्टी विधानको धारा १७ को केन्द्रीय महाधिवेशन प्रतिनिधिको कार्यविधिको [&#8230;]",
  "content_text": "काठमाडौं, २ असोज । नेपाली कांग्रेसका सहमहामन्त्री जीवन परियारले पार्टीको पुनर्गठनको लागि भन्दै विशेष महाधिवेशनको माग गरेका छन् । अहिलेको कठिन परिस्थितिमा पार्टीको पुनर्गठन, नेतृत्वले त्याग गर्नुपर्ने, नेतृत्वको बहिर्गमनजस्ता विविध मागहरु आइरहेको उल्लेख गर्दै उनले पार्टी विधानको धारा १७ अनुसार विशेष महाधिवेशनको माग गरेका हुन् । ‘पार्टी विधानको धारा १७ को केन्द्रीय महाधिवेशन प्रतिनिधिको कार्यविधिको […]",
  "fetched_at": "2025-09-18T06:33:36.971827Z",
  "id": "c186746f62355b6b9a3f8ff3798e84bce5aee3c3758118a918ff5489bed153b9",
  "images": [],
  "lang": "ne",
  "published_at": "2025-09-18T06:25:17Z",
  "source": {
    "domain": "reportersnepal.com",
    "id": "reportersnepal",
    "name": "Reporters Nepal"
  },
  "summary": "काठमाडौं, २ असोज । नेपाली कांग्रेसका सहमहामन्त्री जीवन परियारले पार्टीको पुनर्गठनको लागि भन्दै विशेष महाधिवेशनको माग गरेका छन् । अहिलेको कठिन परिस्थितिमा पार्टीको पुनर्गठन, नेतृत्वले त्याग गर्नुपर्ने, नेतृत्वको बहिर्गमनजस्ता विविध मागहरु आइरहेको उल्लेख गर्दै उनले पार्टी विधानको धारा १७ अनुसार विशेष महाधिवेशनको माग गरेका हुन् । ‘पार्टी विधानको धारा १७ को केन्द्रीय महाधिवेशन प्रतिनिधिको कार्यविधिको [&#8230;]",
  "tags": null,
  "title": "कांग्रेस सह-महामन्त्री परियारद्वारा विशेष महाधिवेशनको माग",
  "url": "https://www.reportersnepal.com/2025/09/1129863/",
  "version": 1
}