{
  "author": "",
  "content": "खबरहब\n८ आश्विन २०८२, बुधबार\nपढ्न लाग्ने समय :\n< 1\nमिनेट\n168\nShares",
  "description": "गुल्मीमा चट्याङ लागेर तीन जना घाइते देश/प्रदेश",
  "domain": "khabarhub.com",
  "enhanced": true,
  "fetched_at": "2025-09-24T17:56:24.051889Z",
  "id": "1db19a52c968bae1a2672dfc5477953add0c04961e0341603a4ef56593c29a31",
  "images": [
    "https://www.khabarhub.com/wp-content/uploads/2025/08/800X100px-2.jpg",
    "https://www.khabarhub.com/wp-content/uploads/2025/07/WhatsApp-Image-2025-07-31-at-2.34.58-PM.jpeg",
    "https://www.khabarhub.com/wp-content/uploads/2020/07/chatyang.jpg",
    "https://www.khabarhub.com/wp-content/uploads/2019/01/logo-150x150.png"
  ],
  "language": "en",
  "metadata": {
    "json_ld": [
      {
        "@context": "https://schema.org",
        "@graph": [
          {
            "@id": "https://khabarhub.com/2025/24/856695/#article",
            "@type": "Article",
            "articleSection": [
              "देश/प्रदेश"
            ],
            "author": {
              "@id": "https://khabarhub.com/#/schema/person/e7150f557f77c19e3e9e088ccc9a3327",
              "name": "खबरहब"
            },
            "dateModified": "2025-09-24T16:07:10+00:00",
            "datePublished": "2025-09-24T16:07:08+00:00",
            "headline": "गुल्मीमा चट्याङ लागेर तीन जना घाइते",
            "image": {
              "@id": "https://khabarhub.com/2025/24/856695/#primaryimage"
            },
            "inLanguage": "en-US",
            "isPartOf": {
              "@id": "https://khabarhub.com/2025/24/856695/"
            },
            "mainEntityOfPage": {
              "@id": "https://khabarhub.com/2025/24/856695/"
            },
            "publisher": {
              "@id": "https://khabarhub.com/#organization"
            },
            "thumbnailUrl": "https://www.khabarhub.com/wp-content/uploads/2020/07/chatyang.jpg",
            "wordCount": 0
          },
          {
            "@id": "https://khabarhub.com/2025/24/856695/",
            "@type": "WebPage",
            "dateModified": "2025-09-24T16:07:10+00:00",
            "datePublished": "2025-09-24T16:07:08+00:00",
            "description": "गुल्मीमा चट्याङ लागेर तीन जना घाइते देश/प्रदेश",
            "image": {
              "@id": "https://khabarhub.com/2025/24/856695/#primaryimage"
            },
            "inLanguage": "en-US",
            "isPartOf": {
              "@id": "https://khabarhub.com/#website"
            },
            "name": "गुल्मीमा चट्याङ लागेर तीन जना घाइते | Khabarhub",
            "potentialAction": [
              {
                "@type": "ReadAction",
                "target": [
                  "https://khabarhub.com/2025/24/856695/"
                ]
              }
            ],
            "primaryImageOfPage": {
              "@id": "https://khabarhub.com/2025/24/856695/#primaryimage"
            },
            "thumbnailUrl": "https://www.khabarhub.com/wp-content/uploads/2020/07/chatyang.jpg",
            "url": "https://khabarhub.com/2025/24/856695/"
          },
          {
            "@id": "https://khabarhub.com/2025/24/856695/#primaryimage",
            "@type": "ImageObject",
            "caption": "प्रतिकात्मक तस्वीर",
            "contentUrl": "https://www.khabarhub.com/wp-content/uploads/2020/07/chatyang.jpg",
            "height": 539,
            "inLanguage": "en-US",
            "url": "https://www.khabarhub.com/wp-content/uploads/2020/07/chatyang.jpg",
            "width": 1200
          },
          {
            "@id": "https://khabarhub.com/#website",
            "@type": "WebSite",
            "description": "Nepal&#039;s Trusted News Source",
            "inLanguage": "en-US",
            "name": "Khabarhub",
            "potentialAction": [
              {
                "@type": "SearchAction",
                "query-input": {
                  "@type": "PropertyValueSpecification",
                  "valueName": "search_term_string",
                  "valueRequired": true
                },
                "target": {
                  "@type": "EntryPoint",
                  "urlTemplate": "https://khabarhub.com/?s={search_term_string}"
                }
              }
            ],
            "publisher": {
              "@id": "https://khabarhub.com/#organization"
            },
            "url": "https://khabarhub.com/"
          },
          {
            "@id": "https://khabarhub.com/#organization",
            "@type": "Organization",
            "image": {
              "@id": "https://khabarhub.com/#/schema/logo/image/"
            },
            "logo": {
              "@id": "https://khabarhub.com/#/schema/logo/image/",
              "@type": "ImageObject",
              "caption": "Khabarhub.com",
              "contentUrl": "https://i0.wp.com/www.khabarhub.com/wp-content/uploads/2019/02/logo.png?fit=339%2C80&ssl=1",
              "height": 80,
              "inLanguage": "en-US",
              "url": "https://i0.wp.com/www.khabarhub.com/wp-content/uploads/2019/02/logo.png?fit=339%2C80&ssl=1",
              "width": 339
            },
            "name": "Khabarhub.com",
            "sameAs": [
              "https://www.facebook.com/khabarhubonline/",
              "https://x.com/khabarhubonline"
            ],
            "url": "https://khabarhub.com/"
          },
          {
            "@id": "https://khabarhub.com/#/schema/person/e7150f557f77c19e3e9e088ccc9a3327",
            "@type": "Person",
            "image": {
              "@id": "https://khabarhub.com/#/schema/person/image/",
              "@type": "ImageObject",
              "caption": "खबरहब",
              "contentUrl": "https://www.khabarhub.com/wp-content/uploads/2019/01/logo-96x96.png",
              "inLanguage": "en-US",
              "url": "https://www.khabarhub.com/wp-content/uploads/2019/01/logo-96x96.png"
            },
            "name": "खबरहब",
            "url": "https://khabarhub.com/author/newsadmin/"
          }
        ]
      }
    ],
    "microdata": [],
    "opengraph": [
      {
        "namespace": {
          "og": "http://ogp.me/ns#"
        },
        "properties": [
          [
            "og:title",
            "गुल्मीमा चट्याङ लागेर तीन जना घाइते"
          ],
          [
            "og:type",
            "article"
          ],
          [
            "og:description",
            "गुल्मी – गुल्मीमा चट्याङ लागेर तीन जना घाइते भएका छन् । चट्याङका कारण जिल्लामा तीनवटा गोरुसमेत मरेका छन् । आज अचानक मौसममा आएको परिवर्तनसँगै जिल्लामा चट्याङले क्षति पुर्‍याएको हो । चट्याङका कारण जिल्लाको इस्मा गाउँपालिका(४ दोहोलीकी ४६ वर्षीया निर्मला खत्री, इस्मा(५ बेसारीकी २५ वर्षीया कालीका खत्री र धुर्कोट गाउँपालिका(७ वाग्ला धरमपानीका ५८ वर्षीय कृष्णप्रसाद पन्थी […]"
          ],
          [
            "og:url",
            "https://khabarhub.com/2025/24/856695/"
          ],
          [
            "og:site_name",
            "Khabarhub"
          ],
          [
            "og:image",
            "https://www.khabarhub.com/wp-content/uploads/2020/07/chatyang.jpg"
          ]
        ]
      }
    ],
    "raw": {
      "json-ld": [
        {
          "@context": "https://schema.org",
          "@graph": [
            {
              "@id": "https://khabarhub.com/2025/24/856695/#article",
              "@type": "Article",
              "articleSection": [
                "देश/प्रदेश"
              ],
              "author": {
                "@id": "https://khabarhub.com/#/schema/person/e7150f557f77c19e3e9e088ccc9a3327",
                "name": "खबरहब"
              },
              "dateModified": "2025-09-24T16:07:10+00:00",
              "datePublished": "2025-09-24T16:07:08+00:00",
              "headline": "गुल्मीमा चट्याङ लागेर तीन जना घाइते",
              "image": {
                "@id": "https://khabarhub.com/2025/24/856695/#primaryimage"
              },
              "inLanguage": "en-US",
              "isPartOf": {
                "@id": "https://khabarhub.com/2025/24/856695/"
              },
              "mainEntityOfPage": {
                "@id": "https://khabarhub.com/2025/24/856695/"
              },
              "publisher": {
                "@id": "https://khabarhub.com/#organization"
              },
              "thumbnailUrl": "https://www.khabarhub.com/wp-content/uploads/2020/07/chatyang.jpg",
              "wordCount": 0
            },
            {
              "@id": "https://khabarhub.com/2025/24/856695/",
              "@type": "WebPage",
              "dateModified": "2025-09-24T16:07:10+00:00",
              "datePublished": "2025-09-24T16:07:08+00:00",
              "description": "गुल्मीमा चट्याङ लागेर तीन जना घाइते देश/प्रदेश",
              "image": {
                "@id": "https://khabarhub.com/2025/24/856695/#primaryimage"
              },
              "inLanguage": "en-US",
              "isPartOf": {
                "@id": "https://khabarhub.com/#website"
              },
              "name": "गुल्मीमा चट्याङ लागेर तीन जना घाइते | Khabarhub",
              "potentialAction": [
                {
                  "@type": "ReadAction",
                  "target": [
                    "https://khabarhub.com/2025/24/856695/"
                  ]
                }
              ],
              "primaryImageOfPage": {
                "@id": "https://khabarhub.com/2025/24/856695/#primaryimage"
              },
              "thumbnailUrl": "https://www.khabarhub.com/wp-content/uploads/2020/07/chatyang.jpg",
              "url": "https://khabarhub.com/2025/24/856695/"
            },
            {
              "@id": "https://khabarhub.com/2025/24/856695/#primaryimage",
              "@type": "ImageObject",
              "caption": "प्रतिकात्मक तस्वीर",
              "contentUrl": "https://www.khabarhub.com/wp-content/uploads/2020/07/chatyang.jpg",
              "height": 539,
              "inLanguage": "en-US",
              "url": "https://www.khabarhub.com/wp-content/uploads/2020/07/chatyang.jpg",
              "width": 1200
            },
            {
              "@id": "https://khabarhub.com/#website",
              "@type": "WebSite",
              "description": "Nepal&#039;s Trusted News Source",
              "inLanguage": "en-US",
              "name": "Khabarhub",
              "potentialAction": [
                {
                  "@type": "SearchAction",
                  "query-input": {
                    "@type": "PropertyValueSpecification",
                    "valueName": "search_term_string",
                    "valueRequired": true
                  },
                  "target": {
                    "@type": "EntryPoint",
                    "urlTemplate": "https://khabarhub.com/?s={search_term_string}"
                  }
                }
              ],
              "publisher": {
                "@id": "https://khabarhub.com/#organization"
              },
              "url": "https://khabarhub.com/"
            },
            {
              "@id": "https://khabarhub.com/#organization",
              "@type": "Organization",
              "image": {
                "@id": "https://khabarhub.com/#/schema/logo/image/"
              },
              "logo": {
                "@id": "https://khabarhub.com/#/schema/logo/image/",
                "@type": "ImageObject",
                "caption": "Khabarhub.com",
                "contentUrl": "https://i0.wp.com/www.khabarhub.com/wp-content/uploads/2019/02/logo.png?fit=339%2C80&ssl=1",
                "height": 80,
                "inLanguage": "en-US",
                "url": "https://i0.wp.com/www.khabarhub.com/wp-content/uploads/2019/02/logo.png?fit=339%2C80&ssl=1",
                "width": 339
              },
              "name": "Khabarhub.com",
              "sameAs": [
                "https://www.facebook.com/khabarhubonline/",
                "https://x.com/khabarhubonline"
              ],
              "url": "https://khabarhub.com/"
            },
            {
              "@id": "https://khabarhub.com/#/schema/person/e7150f557f77c19e3e9e088ccc9a3327",
              "@type": "Person",
              "image": {
                "@id": "https://khabarhub.com/#/schema/person/image/",
                "@type": "ImageObject",
                "caption": "खबरहब",
                "contentUrl": "https://www.khabarhub.com/wp-content/uploads/2019/01/logo-96x96.png",
                "inLanguage": "en-US",
                "url": "https://www.khabarhub.com/wp-content/uploads/2019/01/logo-96x96.png"
              },
              "name": "खबरहब",
              "url": "https://khabarhub.com/author/newsadmin/"
            }
          ]
        }
      ],
      "microdata": [],
      "opengraph": [
        {
          "namespace": {
            "og": "http://ogp.me/ns#"
          },
          "properties": [
            [
              "og:title",
              "गुल्मीमा चट्याङ लागेर तीन जना घाइते"
            ],
            [
              "og:type",
              "article"
            ],
            [
              "og:description",
              "गुल्मी – गुल्मीमा चट्याङ लागेर तीन जना घाइते भएका छन् । चट्याङका कारण जिल्लामा तीनवटा गोरुसमेत मरेका छन् । आज अचानक मौसममा आएको परिवर्तनसँगै जिल्लामा चट्याङले क्षति पुर्‍याएको हो । चट्याङका कारण जिल्लाको इस्मा गाउँपालिका(४ दोहोलीकी ४६ वर्षीया निर्मला खत्री, इस्मा(५ बेसारीकी २५ वर्षीया कालीका खत्री र धुर्कोट गाउँपालिका(७ वाग्ला धरमपानीका ५८ वर्षीय कृष्णप्रसाद पन्थी […]"
            ],
            [
              "og:url",
              "https://khabarhub.com/2025/24/856695/"
            ],
            [
              "og:site_name",
              "Khabarhub"
            ],
            [
              "og:image",
              "https://www.khabarhub.com/wp-content/uploads/2020/07/chatyang.jpg"
            ]
          ]
        }
      ]
    }
  },
  "og_description": "",
  "og_image": "",
  "og_site_name": "",
  "og_title": "",
  "og_type": "",
  "published_at": "2025-09-24T16:07:08Z",
  "source": "Khabarhub",
  "store_path": "_store/1d/1db19a52c968bae1a2672dfc5477953add0c04961e0341603a4ef56593c29a31.json",
  "title": "गुल्मीमा चट्याङ लागेर तीन जना घाइते",
  "url": "https://khabarhub.com/2025/24/856695/",
  "version": 1
}