{
  "byline": null,
  "canonical_hash": "5bf1a1e81587edb23818f909f03412fc63854708f1350e4b837947b5637267de",
  "content_html": "प्रधानमन्त्री सुशिला कार्कीलाई गृह मन्त्री माग गर्न धरान उपमहानगरपालिकाका मेयर हर्क साम्पाङ प्रधानमन्त्री निवास बालुवाटार पुगेको खुलेको छ।",
  "content_text": "प्रधानमन्त्री सुशिला कार्कीलाई गृह मन्त्री माग गर्न धरान उपमहानगरपालिकाका मेयर हर्क साम्पाङ प्रधानमन्त्री निवास बालुवाटार पुगेको खुलेको छ।",
  "fetched_at": "2025-09-14T14:26:08.777509Z",
  "id": "870a1026d4cb437957a13e395138e08d1e7bfa483d2e7e4859d4e30450dd3b0d",
  "images": [],
  "lang": "ne",
  "published_at": "2025-09-14T14:24:00Z",
  "source": {
    "domain": "setopati.com",
    "id": "setopati",
    "name": "सेतोपाटी"
  },
  "summary": "प्रधानमन्त्री सुशिला कार्कीलाई गृह मन्त्री माग गर्न धरान उपमहानगरपालिकाका मेयर हर्क साम्पाङ प्रधानमन्त्री निवास बालुवाटार पुगेको खुलेको छ।",
  "tags": null,
  "title": "गृहमन्त्री बनाउन माग गर्दै बालुवाटार पुगेका थिए हर्क साम्पाङ",
  "url": "https://www.setopati.com/politics/369324",
  "version": 1
}