{
  "content": "",
  "description": "काठमाडौँ । राष्ट्रिय स्तरका निजामती ट्रेड युनियनहरूले सार्वजनिक प्रशासनको रूपान्तरण कुनै व्यक्ति वा पद विशेषको बर्खास्ती वा राजीनामा मागेर सम्भव नहुने स्पष्ट पारेका छन्। उनीहरूले संविधान, ऐन र नियमलाई समयानुकूल निर्माण वा संशोधनमार्फत मात्र रूपान्तरण सम्भव हुने र त्यसका लागि सबै कर्मचारीहरूको साझा अठोट अपरिहार्य हुने धारणा व्यक्त गरेका छन्। नेपाल निजामती कर्मचारी सङ्गठन, नेपाल […]",
  "domain": "prasashan.com",
  "fetched_at": "2025-09-24T09:55:36.116779Z",
  "id": "afab5971f61ccc531c7526e9d7ebd7e5a0c18eacc89bf23efce7a134961f2d03",
  "images": [],
  "published_at": "2025-09-24T09:08:17Z",
  "source": "Prashasan",
  "store_path": "_store/af/afab5971f61ccc531c7526e9d7ebd7e5a0c18eacc89bf23efce7a134961f2d03.json",
  "title": "सार्वजनिक प्रशासन रूपान्तरणको नाममा पद विशेष राजीनामा माग्नु समाधान होइन : संयुक्त ट्रेड युनियन",
  "url": "https://www.prasashan.com/2025/09/24/703877/",
  "version": 1
}