{
  "byline": null,
  "canonical_hash": "c2a5c5dc622fee1d62031d39a38ffd112006ae5e21cc27ddfae7d525f3518eb0",
  "content_html": "काठमाडौं : जेनजी आन्दोलनका अगुवा र राष्ट्रपतिबीच भएको सम्झौता सार्वजनिक गरिएको छ।जेनजी लिडर सुदन गुरुङको हामी नेपाल नामक संस्थाका तर्फबाट सार्वजनिक गरिएको सम्झौता पत्र १३ बुँदे छ। गत शुक्रबार राति भएको यही सम्झौता अनुसार सुशीला कार्की अन्तरिम सरकारको प्रधानमन्त्री नियुक्त भएकी थिइन्।&nbsp;सम्झौतापत्रमा सुदन गुरुङसहित विभिन्न जेनजी समूहलाई समर्थकका रुपमा राखिएको छ। सार्वजनिक सम्झौता पत्रमा आन्दोलनरत पक्षको तर्फबाट र राष्ट्रपति रामचन्द्र पौडेलका तर्फबाट हस्ताक्षर गरिएको छैन। साक्षीमा नेपालको प्रधा",
  "content_text": "काठमाडौं : जेनजी आन्दोलनका अगुवा र राष्ट्रपतिबीच भएको सम्झौता सार्वजनिक गरिएको छ।जेनजी लिडर सुदन गुरुङको हामी नेपाल नामक संस्थाका तर्फबाट सार्वजनिक गरिएको सम्झौता पत्र १३ बुँदे छ। गत शुक्रबार राति भएको यही सम्झौता अनुसार सुशीला कार्की अन्तरिम सरकारको प्रधानमन्त्री नियुक्त भएकी थिइन्। सम्झौतापत्रमा सुदन गुरुङसहित विभिन्न जेनजी समूहलाई समर्थकका रुपमा राखिएको छ। सार्वजनिक सम्झौता पत्रमा आन्दोलनरत पक्षको तर्फबाट र राष्ट्रपति रामचन्द्र पौडेलका तर्फबाट हस्ताक्षर गरिएको छैन। साक्षीमा नेपालको प्रधा",
  "fetched_at": "2025-09-16T10:43:01.926040Z",
  "id": "08c064d0dfe07697afb859f21b5481f3366987e7af9a02a1d9a1b12ac46405ed",
  "images": [],
  "lang": "ne",
  "published_at": null,
  "source": {
    "domain": "thahakhabar.com",
    "id": "thahakhabar",
    "name": "थाहा खबर"
  },
  "summary": "काठमाडौं : जेनजी आन्दोलनका अगुवा र राष्ट्रपतिबीच भएको सम्झौता सार्वजनिक गरिएको छ।जेनजी लिडर सुदन गुरुङको हामी नेपाल नामक संस्थाका तर्फबाट सार्वजनिक गरिएको सम्झौता पत्र १३ बुँदे छ। गत शुक्रबार राति भएको यही सम्झौता अनुसार सुशीला कार्की अन्तरिम सरकारको प्रधानमन्त्री नियुक्त भएकी थिइन्।&nbsp;सम्झौतापत्रमा सुदन गुरुङसहित विभिन्न जेनजी समूहलाई समर्थकका रुपमा राखिएको छ। सार्वजनिक सम्झौता पत्रमा आन्दोलनरत पक्षको तर्फबाट र राष्ट्रपति रामचन्द्र पौडेलका तर्फबाट हस्ताक्षर गरिएको छैन। साक्षीमा नेपालको प्रधा",
  "tags": null,
  "title": "‘हामी नेपाल’ले सार्वजनिक गर्यो राष्ट्रपतिसँगको सम्झौता",
  "url": "https://thahakhabar.com/news/235533",
  "version": 1
}