{
  "byline": "रिपोर्टर्स डेस्क",
  "canonical_hash": "22262f2ca9bb4f2b0b180ea53dbbc077d7b2904d91ebad9f5efd5d4342c54aff",
  "content_html": "जनकपुरधाम, ४ असोज । मधेस प्रदेश सरकारका मुख्यमन्त्री सतिशकुमार सिंहले जेनजीको प्रदर्शनका क्रममा तोडफोड तथा आगजनीको कारण क्षतिग्रस्त भएका कार्यालयले बडादसैँपछि पूर्ण रुपमा सेवा प्रवाह गर्ने बताएका छन् । उनले आज पत्रकारहरुसँग सङ्क्षिप्त कुराकानी गर्दै जेनजी प्रदर्शनका क्रममा मधेस प्रदेश सरकारको सरकारी निकायमा भौतिक संरचनाको व्यापक क्षति भएकाले यसको मर्मत तथा सुधारमा थप अझै केही [&#8230;]",
  "content_text": "जनकपुरधाम, ४ असोज । मधेस प्रदेश सरकारका मुख्यमन्त्री सतिशकुमार सिंहले जेनजीको प्रदर्शनका क्रममा तोडफोड तथा आगजनीको कारण क्षतिग्रस्त भएका कार्यालयले बडादसैँपछि पूर्ण रुपमा सेवा प्रवाह गर्ने बताएका छन् । उनले आज पत्रकारहरुसँग सङ्क्षिप्त कुराकानी गर्दै जेनजी प्रदर्शनका क्रममा मधेस प्रदेश सरकारको सरकारी निकायमा भौतिक संरचनाको व्यापक क्षति भएकाले यसको मर्मत तथा सुधारमा थप अझै केही […]",
  "fetched_at": "2025-09-20T08:44:59.486679Z",
  "id": "f7c2187f8420008c63083eca5245c71b54f2f08d0dbe9515a826043d3c5d4e6d",
  "images": [],
  "lang": "ne",
  "published_at": "2025-09-20T08:36:54Z",
  "source": {
    "domain": "reportersnepal.com",
    "id": "reportersnepal",
    "name": "Reporters Nepal"
  },
  "summary": "जनकपुरधाम, ४ असोज । मधेस प्रदेश सरकारका मुख्यमन्त्री सतिशकुमार सिंहले जेनजीको प्रदर्शनका क्रममा तोडफोड तथा आगजनीको कारण क्षतिग्रस्त भएका कार्यालयले बडादसैँपछि पूर्ण रुपमा सेवा प्रवाह गर्ने बताएका छन् । उनले आज पत्रकारहरुसँग सङ्क्षिप्त कुराकानी गर्दै जेनजी प्रदर्शनका क्रममा मधेस प्रदेश सरकारको सरकारी निकायमा भौतिक संरचनाको व्यापक क्षति भएकाले यसको मर्मत तथा सुधारमा थप अझै केही [&#8230;]",
  "tags": null,
  "title": "मधेस प्रदेश सरकारका सेवा दसैँपछि पूर्ण रुपमा सञ्चालन हुने",
  "url": "https://www.reportersnepal.com/2025/09/1130800/",
  "version": 1
}