{
  "author": "",
  "content": "90 Sec News\nगृहपृष्ठ\nछुटाउनै नहुने आजका मख्य ११ खबर\nकाठमाडौं। गृहमन्त्री रवि लामिछानेले सत्ता गुमेपछि कांग्रेस बर्बराउन थालेको आरोप लगाएका छन्।\r\nनेकपा एमालेले प्रचण्ड नेतृत्वको सरकारलाई निरन्तरता दिन आफू तयार रहेको बताएको छ। नेपाली कांग्रेसले वर्तमान सरकार अविश्वासको बोझले छिटै पतन हुने दाबी गरेको छ। राज्य व्यवस्था तथा सुशासन समितिले तराईको फास्ट ट्राक समयमै सम्पन्न गर्न सरकारलाई निर्देशन दिएको छ।\nShare\nप्रतिक्रिया दिनुहोस्\nMore News\nहुम्लामा स्थानीय पाठ्यक्रम तयार पार्न समिति गठन\nShare\nबढी ब्याज मागेपछि लक्ष्यअनुसार आन्तरिक ऋण उठाउन असफल सरकार\nShare\nअब निजामती कर्मचारीले टिकटक बनाउन नपाउने\nShare\nदरवार हत्याकाण्ड र गौर हत्याकाण्डको खोजिनीति गर्नुछ : प्रधानमन्त्री\nShare\nसंसदमा आज सांसदहरुले प्रधानमन्त्रीेलाई नीति तथा कामका बारेमा प्रश्न गर्ने\nShare\nबालकृष्ण खाणलाई कांग्रेसबाट निलम्बन गर्न माग गर्दै नेविसंघको प्रदर्शन\nShare\nअष्टलक्ष्मी शाक्यलाई उपराष्ट्रपतिको उम्मेदवार बनाउने एमालेको निर्णय\n1k\nViews\nShare\nजर्ज र काइल चम्किदा नामिबियामाथि स्कटल्याण्डको शानदार जित\nShare\nसामुदायिक रेडियोलाई पछि पार्ने सरकारको नीति छैनः उपप्रधानमन्त्री पौडेल\nShare\nभारतीय दुतावासले मनायो गणतन्त्र दिवस\nShare\nअर्थ मन्त्रालयद्वारा चालु खर्च घटाउन मापदण्ड जारी, प्रशासनिक खर्च न्यूनतम १५ प्रतिशतले घटाउने\nShare",
  "description": "",
  "domain": "dekhapadhi.com",
  "enhanced": true,
  "fetched_at": "2025-09-23T14:23:19.632492Z",
  "id": "25b3315f5b4dc7be5e358daa9e7b2f479c745f079153e112ab76a20ba057358d",
  "images": [],
  "language": "en",
  "metadata": {
    "json_ld": [],
    "microdata": [],
    "opengraph": [
      {
        "namespace": {
          "og": "http://ogp.me/ns#"
        },
        "properties": [
          [
            "og:title",
            "छुटाउनै नहुने आजका मख्य ११ खबर"
          ],
          [
            "og:description",
            "काठमाडौं। गृहमन्त्री रवि लामिछानेले सत्ता गुमेपछि कांग्रेस बर्बराउन थालेको आरोप लगाएका छन्।\r\nनेकपा एमालेले प्रचण्ड नेतृत्वको सरकारलाई निरन्तरता दिन आफू तयार रहेको बताएको छ। नेपाली कांग्रेसले वर्तमान सरकार अविश्वासको बोझले छिटै पतन हुने दाबी गरेको छ। राज्य व्यवस्था तथा सुशासन समितिले तराईको फास्ट ट्राक समयमै सम्पन्न गर्न सरकारलाई निर्देशन दिएको छ।"
          ],
          [
            "og:image",
            "https://www.dekhapadhi.com/uploads/posts/16125500.jpg"
          ],
          [
            "og:url",
            "https://www.dekhapadhi.com/detail/ninety-sec-news/69719"
          ],
          [
            "og:type",
            "article"
          ]
        ]
      }
    ],
    "raw": {
      "json-ld": [],
      "microdata": [],
      "opengraph": [
        {
          "namespace": {
            "og": "http://ogp.me/ns#"
          },
          "properties": [
            [
              "og:title",
              "छुटाउनै नहुने आजका मख्य ११ खबर"
            ],
            [
              "og:description",
              "काठमाडौं। गृहमन्त्री रवि लामिछानेले सत्ता गुमेपछि कांग्रेस बर्बराउन थालेको आरोप लगाएका छन्।\r\nनेकपा एमालेले प्रचण्ड नेतृत्वको सरकारलाई निरन्तरता दिन आफू तयार रहेको बताएको छ। नेपाली कांग्रेसले वर्तमान सरकार अविश्वासको बोझले छिटै पतन हुने दाबी गरेको छ। राज्य व्यवस्था तथा सुशासन समितिले तराईको फास्ट ट्राक समयमै सम्पन्न गर्न सरकारलाई निर्देशन दिएको छ।"
            ],
            [
              "og:image",
              "https://www.dekhapadhi.com/uploads/posts/16125500.jpg"
            ],
            [
              "og:url",
              "https://www.dekhapadhi.com/detail/ninety-sec-news/69719"
            ],
            [
              "og:type",
              "article"
            ]
          ]
        }
      ]
    }
  },
  "og_description": "",
  "og_image": "",
  "og_site_name": "",
  "og_title": "",
  "og_type": "",
  "published_at": "2024-04-21T04:22:00Z",
  "source": "Dekhapadhi",
  "store_path": "_store/25/25b3315f5b4dc7be5e358daa9e7b2f479c745f079153e112ab76a20ba057358d.json",
  "title": "छुटाउनै नहुने आजका मख्य ११ खबर",
  "url": "https://www.dekhapadhi.com/detail/ninety-sec-news/69719",
  "version": 1
}