{
  "author": "शिलापत्र संवाददाता :: तमोर दुर्घटना अपडेट: उद्धारमा खटियो नेपाली सेना ",
  "content": "तमोर दुर्घटना अपडेट: उद्धारमा खटियो नेपाली सेना\n-\nशिलापत्र संवाददाता\n|\n                                                    शनिबार, असोज १८, २०८२\nA\n+\nA\nA\n-\nपाँचथरको कुम्मायक गाउँपालिका– ३ को कात्तिकेमा भएको दुर्घटनामा परेका घाइतेको नेपाली सेनाले उद्धार गरेको छ ।\nताप्लेजुङबाट धरान जाँदै गरेको जिप आज बिहान कात्तिकेमा दुर्घटना भएको थियो । उक्त दुर्घटनामा परेका यात्रुहरूलाई स्थानीय बासिन्दा र अन्य सुरक्षा निकायको सहयोगमा नेपाली सेना वीर दल गणले उद्धार गरेको हो ।\nदुर्घटनामा परेर ६ जनाको मृत्यु भएको छ । भने, एक बालिकसहित ६ जना घाइते भएका छन् ।\nप्रकाशित मिति: शनिबार, असोज १८, २०८२\n१५:२७\nशिलापत्र संवाददाता\nप्रतिक्रिया दिनुहोस्\nसमाचार\nसञ्चार सम्पर्क अवरुद्ध भए तत्काल जानकारी गराउन सञ्चारमन्त्री खरेलको आग्रह\nसञ्चार सम्पर्क अवरुद्ध भए तत्काल जानकारी गराउन सञ्चारमन्त्री खरेलको आग्रह\n1 min read\nसमाचार\nतमोर दुर्घटना अपडेट: उद्धारमा खटियो नेपाली सेना\nतमोर दुर्घटना अपडेट: उद्धारमा खटियो नेपाली सेना\n1 min read\nसमाचार\nमधेशका विभिन्न स्थानमा वर्षाले सतर्कता तह पार गर्‍यो\nमधेशका विभिन्न स्थानमा वर्षाले सतर्कता तह पार गर्‍यो\n1 min read\nहाम्रो छनौट\nसम्पादकीय\nशोक र शक्तिबीचको दसैँ\nआज देश शोकमा छ । आर्थिक समृद्धिको सपनामा छ । राजनीतिक मात्र होइन, सरकार स्थिरताको पक्षमा छ । दलको आन्तरिक समीक्षा र सुधारको मागमा छ । सामाजिक गतिको बुझाइको अपेक्षामा छ । त्यस अर्थमा जेन–जी आन्दोलनको बलिदानी बहुआयामिक छ ।\n5 min read\nसमाचार\nशोकको छायामा आशाको दसैँ\nयो दसैँमा एउटै कामना छ, एउटै प्रार्थना छ । यही कि हामी सबैले आफ्नो सबैभन्दा ठूलो शक्ति, आफ्नो भोटको सदुपयोग गरौँ । महिषासुरहरूलाई शीर उठाउनबाट रोकौँ ।\n7 min read\nराजनीति\nदण्डहीनताको अन्त्य गर्न तत्कालीन सरकार र आन्दोलनकारीलाई न्यायको कठघरामा उभ्याऊ\n10 min read\nराजनीति\nआप्रवासी श्रम प्रणालीको अर्थ-राजनीति\nजबसम्म श्रम गन्तव्यको रोजगारदाता र त्यहाँको अर्थतन्त्रले बिनाकुनै लगानी सस्तो श्रम पाउने, अनि पेन्सनलगायत सामाजिक सुरक्षाको प्रत्याभूति दिनु नपर्ने अवस्था रहन्छ, यो शोषणकारी आप्रवासी श्रम प्रणाली चली नै रहन्छ ।\n13 min read\nभर्खरै\nबागमती नदीमा पानीको बहाब बढ्यो, सुकुम्वासी बस्ती डुबानमा, सेना परिचालन (तस्वीरहरू)\n1 min read\nसञ्चार सम्पर्क अवरुद्ध भए तत्काल जानकारी गराउन सञ्चारमन्त्री खरेलको आग्रह\n1 min read\nतमोर दुर्घटना अपडेट: उद्धारमा खटियो नेपाली सेना\n1 min read\nमधेशका विभिन्न स्थानमा वर्षाले सतर्कता तह पार गर्‍यो\n1 min read\nअविरल वर्षा: वर्तमान अवस्था र सम्भावित जोखिमबारे मौसम विभागको १० बुँदे अपडेट\n3 min read\nलोकप्रिय\nगुण्डुमा ओलीको भाषण र गृह मन्त्रालयको  वक्तव्य\n3 min read\nबालेनको विरोध गरे 'तेरो लास पनि नभेटिएला' भन्दै धम्काएपछि माजिदले दिए साइबर ब्युरोमा उजुरी\n1 min read\n१७ वर्षपछि पूर्वराजाको हैसियत स्वीकारेका ज्ञानेन्द्र शाह\n2 min read\n‘शिक्षकलाई तलब कस्ले दिन्छ’ भन्ने पनि पत्तो पाएनन् शिक्षामन्त्री पुनले, सच्याए ‘स्टाटस्’\n1 min read\n‘हामी नेपाल’ विवादमा परेपछि सहयोग उठाउन सुदन गुरुङ समूहले अघि सार्‍यो नयाँ ‘आइडिया’\n2 min read\nविचार\nखरानीमा जीवनकाे बिउ खाेज्ने समय, अब यो देश कसले बनाउने ?\n8 min read\nदसैँको मिथिला रूप : आस्था, अन्धविश्वास र आजको विकृति\n10 min read\nशोकको छायामा आशाको दसैँ\n7 min read\nब्लग\nअहिले बुबा हुनु भएको भए...\n10 min read\nखसी चराउन जाँदाको दसैँ झलझली सम्झिन्छुु\n4 min read\nयसपालि त यस्तै भयो आमा, अर्को दसैँमा आउँछु\n1 min read\nशिक्षा\n‘शिक्षकलाई तलब कस्ले दिन्छ’ भन्ने पनि पत्तो पाएनन् शिक्षामन्त्री पुनले, सच्याए ‘स्टाटस्’\n1 min read\nभोलिसम्म शिक्षकको तलब नदिने प्रधानाध्यापकलाई कारबाही गरिनेछ: शिक्षामन्त्री पुन\n1 min read\nसीटीईभीटीलाई शिक्षामन्त्री पुनको चार बुँदे निर्देशन\n1 min read",
  "description": "पाँचथरको कुम्मायक गाउँपालिका– ३ को कात्तिकेमा भएको दुर्घटनामा परेका घाइतेको नेपाली सेनाले उद्धार गरेको छ ।",
  "domain": "shilapatra.com",
  "enhanced": true,
  "fetched_at": "2025-10-04T10:30:40.559191Z",
  "id": "370a90250325d21e9ad66cab3018ead407f4097c804b17c0cde8f349f13048cb",
  "images": [],
  "language": "en",
  "metadata": {
    "json_ld": [],
    "microdata": [],
    "opengraph": [
      {
        "namespace": {
          "og": "http://ogp.me/ns#"
        },
        "properties": [
          [
            "og:title",
            "तमोर दुर्घटना अपडेट: उद्धारमा खटियो नेपाली सेना "
          ],
          [
            "og:url",
            "https://shilapatra.com/detail/168965/"
          ],
          [
            "og:description",
            "पाँचथरको कुम्मायक गाउँपालिका– ३ को कात्तिकेमा भएको दुर्घटनामा परेका घाइतेको नेपाली सेनाले उद्धार गरेको छ ।"
          ],
          [
            "og:image",
            "https://shilapatracdn.de/uploads/posts/nepali-army-accident-resay-1759570946.jpg"
          ],
          [
            "og:type",
            "article"
          ],
          [
            "og:site_name ",
            "तमोर दुर्घटना अपडेट: उद्धारमा खटियो नेपाली सेना "
          ]
        ]
      }
    ],
    "raw": {
      "json-ld": [],
      "microdata": [],
      "opengraph": [
        {
          "namespace": {
            "og": "http://ogp.me/ns#"
          },
          "properties": [
            [
              "og:title",
              "तमोर दुर्घटना अपडेट: उद्धारमा खटियो नेपाली सेना "
            ],
            [
              "og:url",
              "https://shilapatra.com/detail/168965/"
            ],
            [
              "og:description",
              "पाँचथरको कुम्मायक गाउँपालिका– ३ को कात्तिकेमा भएको दुर्घटनामा परेका घाइतेको नेपाली सेनाले उद्धार गरेको छ ।"
            ],
            [
              "og:image",
              "https://shilapatracdn.de/uploads/posts/nepali-army-accident-resay-1759570946.jpg"
            ],
            [
              "og:type",
              "article"
            ],
            [
              "og:site_name ",
              "तमोर दुर्घटना अपडेट: उद्धारमा खटियो नेपाली सेना "
            ]
          ]
        }
      ]
    }
  },
  "og_description": "",
  "og_image": "",
  "og_site_name": "",
  "og_title": "",
  "og_type": "",
  "published_at": "2025-10-04T09:42:00Z",
  "source": "Shilapatra",
  "store_path": "_store/37/370a90250325d21e9ad66cab3018ead407f4097c804b17c0cde8f349f13048cb.json",
  "title": "तमोर दुर्घटना अपडेट: उद्धारमा खटियो नेपाली सेना",
  "url": "https://shilapatra.com/detail/168965",
  "version": 1
}