{
  "author": "नेपाल जापान",
  "content": "कर्पोरेट/पर्यटन\nपर्यटकलाई पदयात्रामा नजान प्रशासनको आग्रह\nनेपाल जापान\nअशोज १८, २०८२\nजिल्ला प्रशासन कार्यालय कास्कीले उच्च हिमाली क्षेत्रमा हिमपात र भारी वर्षाको सम्भावना रहेकाले पदयात्रामा ननिस्कन पर्यटकहरूलाई आग्रह गरेको छ ।\nप्रशासनले आजदेखि आगामी असोज २० गतेसम्म देशभर तथा गण्डकी प्रदेशमा समेत मध्यमदेखि भारी वर्षाको प्रक्षेपण गरिएकाले हिमपातको सम्भावना रहेकाले पदयात्रीहरूलाई सो आग्रह गरेको हो ।\nविश्व प्रख्यात अन्नपूर्ण आधार शिविर (एविसी), मर्दी हिमाल आधार शिविर, मोडल माछापुच्छ्रे ट्रेक, कपुचे पदयात्रा तथा खुमईलगायत क्षेत्रमा पदयात्रामा नजानका लागि सार्वजनिक सूचनामार्फत सचेत गराइएको सहायक प्रमुख जिल्ला अधिकारी शिवप्रसाद लम्सालले बताउनुभयो ।\nउहाँले भन्नुभयो, “उच्च हिमाली क्षेत्रमा हिमपातको सम्भावना रहेको छ । त्यसैले जीउज्यानको सुरक्षालाई ध्यान दिएर ‘ट्रेकिङ’का लागि पदयात्रा क्षेत्रका कुनै पनि स्थानमा ननिस्कन भनेर आग्रह गरेका हौँ ।”\nदसैँको बिदाका कारणले विगतका वर्षहरूमा यहाँका पदयात्रा क्षेत्रमा पदयात्रीहरूको भीड लाग्ने गरेको थियो । यस वर्ष प्रशासनले भारी वर्षा तथा हिमपातको पूर्वानुमानसहित पदयात्रामा नजान अनुरोध गरेपछि पर्यटन क्षेत्र प्रभावित बनेको छ । दसैँ र तिहारको बिदामा पदमार्गहरूका होटल तथा रेष्टुराँ पर्यटकहरूले भरिभराउ हुने गरेका थिए ।\nयसैगरी प्रशासनले वर्षाका कारण बाढीपहिरो, डुबान, हिमपात आदि विपद्जन्य घटना हुनसक्ने भन्दै सबैलाई सचेत रहन तथा घटना घटेमा सम्बन्धित स्थानीय तह, जनप्रतिनिधि, नजिकको प्रहरी एकाइ, सुरक्षा निकायमा सम्पर्क गर्न समेत अनुरोध गरेको छ ।\nनेपाल जापान\nअशोज १८, २०८२",
  "description": "जिल्ला प्रशासन कार्यालय कास्कीले उच्च हिमाली क्षेत्रमा हिमपात र भारी वर्षाको सम्भावना रहेकाले पदयात्रामा ननिस्कन पर्यटकहरूलाई आग्रह गरेको छ । प्रशासनल",
  "domain": "nepaljapan.com",
  "enhanced": true,
  "fetched_at": "2025-10-04T04:32:26.512429Z",
  "id": "940adbd367a539056dd6787ab60768c84947ed10b3ba1ba6424b7d198360aca7",
  "images": [
    "https://nepaljapan.s3.ap-southeast-1.amazonaws.com/Nepal-japan/images/uploads/2023/12/Treking-e1702007254421.jpg",
    "/wp-content/uploads/2021/04/favicon.png"
  ],
  "language": "en",
  "metadata": {
    "json_ld": [
      {
        "@context": "http://schema.org",
        "@type": "Article",
        "articleBody": "जिल्ला प्रशासन कार्यालय कास्कीले उच्च हिमाली क्षेत्रमा हिमपात र भारी वर्षाको सम्भावना रहेकाले पदयात्रामा ननिस्कन पर्यटकहरूलाई आग्रह गरेको छ ।\r\nप्रशासनले आजदेखि आगामी असोज २० गतेसम्म देशभर तथा गण्डकी प्रदेशमा समेत मध्यमदेखि भारी वर्षाको प्रक्षेपण गरिएकाले हिमपातको सम्भावना रहेकाले पदयात्रीहरूलाई सो आग्रह गरेको हो ।\r\nविश्व प्रख्यात अन्नपूर्ण आधार शिविर (एविसी), मर्दी हिमाल आधार शिविर, मोडल माछापुच्छ्रे ट्रेक, कपुचे पदयात्रा तथा खुमईलगायत क्षेत्रमा पदयात्रामा नजानका लागि सार्वजनिक सूचनामार्फत सचेत गराइएको सहायक प्रमुख जिल्ला अधिकारी शिवप्रसाद लम्सालले बताउनुभयो ।\r\nउहाँले भन्नुभयो, “उच्च हिमाली क्षेत्रमा हिमपातको सम्भावना रहेको छ । त्यसैले जीउज्यानको सुरक्षालाई ध्यान दिएर ‘ट्रेकिङ’का लागि पदयात्रा क्षेत्रका कुनै पनि स्थानमा ननिस्कन भनेर आग्रह गरेका हौँ ।”\r\nदसैँको बिदाका कारणले विगतका वर्षहरूमा यहाँका पदयात्रा क्षेत्रमा पदयात्रीहरूको भीड लाग्ने गरेको थियो । यस वर्ष प्रशासनले भारी वर्षा तथा हिमपातको पूर्वानुमानसहित पदयात्रामा नजान अनुरोध गरेपछि पर्यटन क्षेत्र प्रभावित बनेको छ । दसैँ र तिहारको बिदामा पदमार्गहरूका होटल तथा रेष्टुराँ पर्यटकहरूले भरिभराउ हुने गरेका थिए ।\r\nयसैगरी प्रशासनले वर्षाका कारण बाढीपहिरो, डुबान, हिमपात आदि विपद्जन्य घटना हुनसक्ने भन्दै सबैलाई सचेत रहन तथा घटना घटेमा सम्बन्धित स्थानीय तह, जनप्रतिनिधि, नजिकको प्रहरी एकाइ, सुरक्षा निकायमा सम्पर्क गर्न समेत अनुरोध गरेको छ ।",
        "articleSection": "कर्पोरेट/पर्यटन",
        "author": {
          "@type": "Person",
          "name": "नेपाल जापान",
          "url": "https://www.nepaljapan.com/author/yadav/"
        },
        "copyrightHolder": {
          "@id": "#Publisher"
        },
        "copyrightYear": "२०८२",
        "dateCreated": "2025-10-04T11:35:32+09:00",
        "dateModified": "2025-10-04T11:35:32+09:00",
        "datePublished": "2025-10-04T11:35:32+09:00",
        "description": "जिल्ला प्रशासन कार्यालय कास्कीले उच्च हिमाली क्षेत्रमा हिमपात र भारी वर्षाको सम्भावना रहेकाले पदयात्रामा ननिस्कन पर्यटकहरूलाई आग्रह गरेको छ । प्रशासनले आजदेखि आगामी असोज २० गतेसम्म देशभर तथा गण्डकी प्",
        "headline": "पर्यटकलाई पदयात्रामा नजान प्रशासनको आग्रह",
        "image": {
          "@type": "ImageObject",
          "height": 534,
          "url": "https://nepaljapan.s3.ap-southeast-1.amazonaws.com/Nepal-japan/images/uploads/2023/12/Treking-e1702007254421.jpg",
          "width": 1200
        },
        "keywords": "पदयात्रा",
        "mainEntityOfPage": {
          "@id": "https://www.nepaljapan.com/10/04/683610/",
          "@type": "WebPage"
        },
        "name": "पर्यटकलाई पदयात्रामा नजान प्रशासनको आग्रह",
        "publisher": {
          "@id": "#Publisher",
          "@type": "Organization",
          "logo": {
            "@type": "ImageObject",
            "url": "/wp-content/uploads/2021/04/logo.png"
          },
          "name": "Nepal Japan"
        },
        "sourceOrganization": {
          "@id": "#Publisher"
        },
        "url": "https://www.nepaljapan.com/10/04/683610/"
      }
    ],
    "microdata": [],
    "opengraph": [
      {
        "namespace": {
          "og": "http://ogp.me/ns#"
        },
        "properties": [
          [
            "og:title",
            "पर्यटकलाई पदयात्रामा नजान प्रशासनको आग्रह - Nepal Japan"
          ],
          [
            "og:type",
            "article"
          ],
          [
            "og:description",
            "जिल्ला प्रशासन कार्यालय कास्कीले उच्च हिमाली क्षेत्रमा हिमपात र भारी वर्षाको सम्भावना रहेकाले पदयात्"
          ],
          [
            "og:url",
            "https://www.nepaljapan.com/10/04/683610/"
          ],
          [
            "og:site_name",
            "Nepal Japan"
          ],
          [
            "og:image",
            "https://nepaljapan.s3.ap-southeast-1.amazonaws.com/Nepal-japan/images/uploads/2023/12/Treking-e1702007254421-780x470.jpg"
          ]
        ]
      }
    ],
    "raw": {
      "json-ld": [
        {
          "@context": "http://schema.org",
          "@type": "Article",
          "articleBody": "जिल्ला प्रशासन कार्यालय कास्कीले उच्च हिमाली क्षेत्रमा हिमपात र भारी वर्षाको सम्भावना रहेकाले पदयात्रामा ननिस्कन पर्यटकहरूलाई आग्रह गरेको छ ।\r\nप्रशासनले आजदेखि आगामी असोज २० गतेसम्म देशभर तथा गण्डकी प्रदेशमा समेत मध्यमदेखि भारी वर्षाको प्रक्षेपण गरिएकाले हिमपातको सम्भावना रहेकाले पदयात्रीहरूलाई सो आग्रह गरेको हो ।\r\nविश्व प्रख्यात अन्नपूर्ण आधार शिविर (एविसी), मर्दी हिमाल आधार शिविर, मोडल माछापुच्छ्रे ट्रेक, कपुचे पदयात्रा तथा खुमईलगायत क्षेत्रमा पदयात्रामा नजानका लागि सार्वजनिक सूचनामार्फत सचेत गराइएको सहायक प्रमुख जिल्ला अधिकारी शिवप्रसाद लम्सालले बताउनुभयो ।\r\nउहाँले भन्नुभयो, “उच्च हिमाली क्षेत्रमा हिमपातको सम्भावना रहेको छ । त्यसैले जीउज्यानको सुरक्षालाई ध्यान दिएर ‘ट्रेकिङ’का लागि पदयात्रा क्षेत्रका कुनै पनि स्थानमा ननिस्कन भनेर आग्रह गरेका हौँ ।”\r\nदसैँको बिदाका कारणले विगतका वर्षहरूमा यहाँका पदयात्रा क्षेत्रमा पदयात्रीहरूको भीड लाग्ने गरेको थियो । यस वर्ष प्रशासनले भारी वर्षा तथा हिमपातको पूर्वानुमानसहित पदयात्रामा नजान अनुरोध गरेपछि पर्यटन क्षेत्र प्रभावित बनेको छ । दसैँ र तिहारको बिदामा पदमार्गहरूका होटल तथा रेष्टुराँ पर्यटकहरूले भरिभराउ हुने गरेका थिए ।\r\nयसैगरी प्रशासनले वर्षाका कारण बाढीपहिरो, डुबान, हिमपात आदि विपद्जन्य घटना हुनसक्ने भन्दै सबैलाई सचेत रहन तथा घटना घटेमा सम्बन्धित स्थानीय तह, जनप्रतिनिधि, नजिकको प्रहरी एकाइ, सुरक्षा निकायमा सम्पर्क गर्न समेत अनुरोध गरेको छ ।",
          "articleSection": "कर्पोरेट/पर्यटन",
          "author": {
            "@type": "Person",
            "name": "नेपाल जापान",
            "url": "https://www.nepaljapan.com/author/yadav/"
          },
          "copyrightHolder": {
            "@id": "#Publisher"
          },
          "copyrightYear": "२०८२",
          "dateCreated": "2025-10-04T11:35:32+09:00",
          "dateModified": "2025-10-04T11:35:32+09:00",
          "datePublished": "2025-10-04T11:35:32+09:00",
          "description": "जिल्ला प्रशासन कार्यालय कास्कीले उच्च हिमाली क्षेत्रमा हिमपात र भारी वर्षाको सम्भावना रहेकाले पदयात्रामा ननिस्कन पर्यटकहरूलाई आग्रह गरेको छ । प्रशासनले आजदेखि आगामी असोज २० गतेसम्म देशभर तथा गण्डकी प्",
          "headline": "पर्यटकलाई पदयात्रामा नजान प्रशासनको आग्रह",
          "image": {
            "@type": "ImageObject",
            "height": 534,
            "url": "https://nepaljapan.s3.ap-southeast-1.amazonaws.com/Nepal-japan/images/uploads/2023/12/Treking-e1702007254421.jpg",
            "width": 1200
          },
          "keywords": "पदयात्रा",
          "mainEntityOfPage": {
            "@id": "https://www.nepaljapan.com/10/04/683610/",
            "@type": "WebPage"
          },
          "name": "पर्यटकलाई पदयात्रामा नजान प्रशासनको आग्रह",
          "publisher": {
            "@id": "#Publisher",
            "@type": "Organization",
            "logo": {
              "@type": "ImageObject",
              "url": "/wp-content/uploads/2021/04/logo.png"
            },
            "name": "Nepal Japan"
          },
          "sourceOrganization": {
            "@id": "#Publisher"
          },
          "url": "https://www.nepaljapan.com/10/04/683610/"
        }
      ],
      "microdata": [],
      "opengraph": [
        {
          "namespace": {
            "og": "http://ogp.me/ns#"
          },
          "properties": [
            [
              "og:title",
              "पर्यटकलाई पदयात्रामा नजान प्रशासनको आग्रह - Nepal Japan"
            ],
            [
              "og:type",
              "article"
            ],
            [
              "og:description",
              "जिल्ला प्रशासन कार्यालय कास्कीले उच्च हिमाली क्षेत्रमा हिमपात र भारी वर्षाको सम्भावना रहेकाले पदयात्"
            ],
            [
              "og:url",
              "https://www.nepaljapan.com/10/04/683610/"
            ],
            [
              "og:site_name",
              "Nepal Japan"
            ],
            [
              "og:image",
              "https://nepaljapan.s3.ap-southeast-1.amazonaws.com/Nepal-japan/images/uploads/2023/12/Treking-e1702007254421-780x470.jpg"
            ]
          ]
        }
      ]
    }
  },
  "og_description": "",
  "og_image": "https://nepaljapan.s3.ap-southeast-1.amazonaws.com/Nepal-japan/images/uploads/2023/12/Treking-e1702007254421.jpg",
  "og_site_name": "",
  "og_title": "",
  "og_type": "",
  "published_at": "2025-10-04T02:35:32Z",
  "source": "NepalJapan",
  "store_path": "_store/94/940adbd367a539056dd6787ab60768c84947ed10b3ba1ba6424b7d198360aca7.json",
  "title": "पर्यटकलाई पदयात्रामा नजान प्रशासनको आग्रह",
  "url": "https://www.nepaljapan.com/10/04/683610/",
  "version": 1
}